[
  {
    "WorkId": "69f4d1df-6def-45a0-bb74-1fe8db18d749",
    "JinoyatVaqti": "zxzxcczx",
    "JinoyatHudud": "zxc",
    "JinoyatJoyi": "zcx",
    "AybElonFIO": "xzc",
    "AyblovProkLavozim": "zxc",
    "AyblovProkFIO": "asdasd",
    "IshProk": "sad",
    "IshPorkFIO": "asd",
    "SSudHukmSana": "asd",
    "SSudyaFIO": "sad",
    "TumanXul": "xasd",
    "ShaharXul": "xa",
    "BoshXul": "hello",
    "person": []
  },
  {
    "WorkId": "11a8569b-b450-4226-b780-c2d39ca8bc9a",
    "JinoyatVaqti": "zxzxcczx",
    "JinoyatHudud": "zxc",
    "JinoyatJoyi": "zcx",
    "AybElonFIO": "Siiiiiiiiiiuuuuuuuuuuu",
    "AyblovProkLavozim": "zxc",
    "AyblovProkFIO": "asdasd",
    "IshProk": "sad",
    "IshPorkFIO": "asd",
    "SSudHukmSana": "asd",
    "SSudyaFIO": "sad",
    "TumanXul": "xasd",
    "ShaharXul": "xa",
    "BoshXul": "hello",
    "person": [
      {
        "UserId": "ea97c8cc-b7e5-46cd-8c03-3f40354f789a",
        "UserName": "Abbas2",
        "Date": "hhhh",
        "Jinsi": "si",
        "Nogironligi": "wewe",
        "RuxiyHolat": "a",
        "Ishjoyi": "aa",
        "lavozimi": "a",
        "OilaAxvoli": "a",
        "VoyYetmaganFarzandi": "sa",
        "MuqaddamSud": "asda",
        "MuqaddamVaqti": "adsaadd",
        "AyblovQisqa": "zxc",
        "UshlanganSana": "zxc",
        "AybElon": "zc",
        "AybModda": "cxz",
        "AybModdaQism": "xzc",
        "AybModdaBandi": "zx",
        "AybOrgani": "xcz",
        "QamoqBolmagan": "xzc",
        "QamoqExtiyot": "asdsad",
        "QamoqUy": "xzc",
        "JinoyatZarar": "sad",
        "ZararQoplanish": "asd",
        "MolMulQoplanish": "asd",
        "QoplanishFoiz": "sad",
        "AybTopish": "asd",
        "Moddasi": "sad",
        "Qismi": "sadasd",
        "Bandi": "sad",
        "AyblovVozKech": "sda",
        "JazoTur": "sad",
        "JazoMiqdori": "sda",
        "ShartliHukm": "sda",
        "Modda57": "sda",
        "Modda96": "asd",
        "MuddatOtib": "sda",
        "XavfYoqot": "sda",
        "Pushaymon": "sda",
        "Yarashgan": "dsa",
        "Kasallik": "sda",
        "AktiTufay": "dsa",
        "userscol": "asd",
        "IjYoq": "das",
        "AmaldaPushay": "dassad",
        "SAybliModda": "sad",
        "SAybliQismi": "asddas",
        "SAybliBandi": "asd",
        "SAydanVoz": "sad",
        "SJazoTuri": "sda",
        "SJazoMiq": "asd",
        "SShartli": "sda",
        "S57Modda": "asd",
        "S96Modda": "ad",
        "SOtibket": "aa",
        "SIjXavf": "a",
        "SAmaldaPush": "a",
        "SYarshMun": "dsa",
        "SKasallik": "sd",
        "SAktAs": "sd",
        "SYoq": "sd",
        "SAmal": "as",
        "Ijkattabol": "asd",
        "Unchaogir": "asdx",
        "Ogir": "adsx",
        "OtaOgir": "asdx"
      }
    ]
  }
]